pdfnofonts/__init__.py
pdfnofonts/cli/__init__.py
pdfnofonts/cli/pdfnofonts.py
pdfnofonts-1.1.0.dist-info/LICENSE
pdfnofonts-1.1.0.dist-info/METADATA
pdfnofonts-1.1.0.dist-info/WHEEL
pdfnofonts-1.1.0.dist-info/entry_points.txt
pdfnofonts-1.1.0.dist-info/top_level.txt
pdfnofonts-1.1.0.dist-info/RECORD
